odoo8_addon_website_mass_mailing_name-8.0.1.0.0.99.dev6-py2.7-nspkg.pth
odoo8_addon_website_mass_mailing_name-8.0.1.0.0.99.dev6.dist-info/DESCRIPTION.rst
odoo8_addon_website_mass_mailing_name-8.0.1.0.0.99.dev6.dist-info/METADATA
odoo8_addon_website_mass_mailing_name-8.0.1.0.0.99.dev6.dist-info/RECORD
odoo8_addon_website_mass_mailing_name-8.0.1.0.0.99.dev6.dist-info/WHEEL
odoo8_addon_website_mass_mailing_name-8.0.1.0.0.99.dev6.dist-info/metadata.json
odoo8_addon_website_mass_mailing_name-8.0.1.0.0.99.dev6.dist-info/namespace_packages.txt
odoo8_addon_website_mass_mailing_name-8.0.1.0.0.99.dev6.dist-info/top_level.txt
odoo_addons/website_mass_mailing_name/README.rst
odoo_addons/website_mass_mailing_name/__init__.py
odoo_addons/website_mass_mailing_name/__openerp__.py
odoo_addons/website_mass_mailing_name/controllers/__init__.py
odoo_addons/website_mass_mailing_name/controllers/main.py
odoo_addons/website_mass_mailing_name/i18n/de.po
odoo_addons/website_mass_mailing_name/i18n/es.po
odoo_addons/website_mass_mailing_name/i18n/fr.po
odoo_addons/website_mass_mailing_name/i18n/sl.po
odoo_addons/website_mass_mailing_name/i18n/website_mass_mailing_name.pot
odoo_addons/website_mass_mailing_name/static/description/icon.png
odoo_addons/website_mass_mailing_name/static/src/css/website_mass_mailing_name.css
odoo_addons/website_mass_mailing_name/static/src/css/website_mass_mailing_name.css.map
odoo_addons/website_mass_mailing_name/static/src/css/website_mass_mailing_name.sass
odoo_addons/website_mass_mailing_name/static/src/js/website_mass_mailing_name.js
odoo_addons/website_mass_mailing_name/static/src/js/website_mass_mailing_name.tour.js
odoo_addons/website_mass_mailing_name/tests/__init__.py
odoo_addons/website_mass_mailing_name/tests/test_ui.py
odoo_addons/website_mass_mailing_name/views/assets.xml
odoo_addons/website_mass_mailing_name/views/snippets.xml
